{
  "kind": "singleType",
  "collectionName": "outstaffings",
  "info": {
    "singularName": "outstaffing",
    "pluralName": "outstaffings",
    "displayName": "outstaffing",
    "description": ""
  },
  "options": {
    "draftAndPublish": true
  },
  "pluginOptions": {},
  "attributes": {
    "main": {
      "type": "component",
      "repeatable": false,
      "component": "main.main-text"
    },
    "approach": {
      "displayName": "approach",
      "type": "component",
      "repeatable": true,
      "component": "services.approach"
    },
    "benefits": {
      "type": "component",
      "repeatable": true,
      "component": "main.main-text"
    },
    "team": {
      "type": "component",
      "repeatable": true,
      "component": "main.title"
    },
    "approachTitle": {
      "type": "string"
    },
    "benefitsTitle": {
      "type": "string"
    },
    "teamTitle": {
      "type": "string"
    },
    "helpingToClients": {
      "displayName": "helpingToClients",
      "type": "component",
      "repeatable": false,
      "component": "services.helping-to-clients"
    },
    "teamButton": {
      "type": "string"
    }
  }
}
